mash/__init__.py
mash/app.py
mash/main.py
mash/mash
mash/utils.py
mash/plugins/__init__.py
mash/plugins/bmc.py
mprov_mash-0.0.8.data/scripts/mash
mprov_mash-0.0.8.dist-info/LICENSE
mprov_mash-0.0.8.dist-info/METADATA
mprov_mash-0.0.8.dist-info/WHEEL
mprov_mash-0.0.8.dist-info/top_level.txt
mprov_mash-0.0.8.dist-info/RECORD
