Metadata-Version: 2.1
Name: mprov_mash
Version: 0.0.8
Summary: mash (mProv Admin Shell)
Home-page: https://github.com/mprov-ng/mash/
Author: Jason Williams
Author-email: jasonw@jhu.edu
Project-URL: Bug Tracker, https://github.com/mprov-ng/mash/issues
Classifier: Programming Language :: Python :: 3
Classifier: Operating System :: POSIX :: Linux
Classifier: License :: OSI Approved :: Apache Software License
Requires-Python: >=3.8
License-File: LICENSE
Requires-Dist: pyyaml
Requires-Dist: jinja2
Requires-Dist: requests
